Workbook

Sheet Products
A1: Product ID (SKU) | B1: Product Name | C1: Category | D1: Brand | E1: Unit Price ₹ | F1: Unit Cost ₹
A2: 5KCXE8ZI | B2: Fresh Anti-Dandruff Cool Mint Shampoo | C2: Personal Care (Shampoo & Soap) | D2: =LEFT(B2, FIND(" ", B2) - 1) -> Fresh | E2: 199 | F2: =Table1[[#This Row],[Unit Price ₹]]*(1-30%) -> 139.3
A3: TOKW9ABP | B3: Fresh Smooth & Shiny Daily Silky Shampoo | C3: Personal Care (Shampoo & Soap) | D3: =LEFT(B3, FIND(" ", B3) - 1) -> Fresh | E3: 185 | F3: =Table1[[#This Row],[Unit Price ₹]]*(1-30%) -> 129.5
A4: Q92TVB4C | B4: Fresh 2-in-1 Shampoo + Conditioner for Kids (Mango Flavor) | C4: Personal Care (Shampoo & Soap) | D4: =LEFT(B4, FIND(" ", B4) - 1) -> Fresh | E4: 225 | F4: =Table1[[#This Row],[Unit Price ₹]]*(1-30%) -> 157.5
A5: B39QQXPS | B5: Purely Apple Cider Vinegar Hair Therapy Shampoo | C5: Personal Care (Shampoo & Soap) | D5: =LEFT(B5, FIND(" ", B5) - 1) -> Purely | E5: 399 | F5: =Table1[[#This Row],[Unit Price ₹]]*(1-30%) -> 279.3
A6: L1RF73ZB | B6: Purely Argan Oil & Moroccan Clay Repair Shampoo | C6: Personal Care (Shampoo & Soap) | D6: =LEFT(B6, FIND(" ", B6) - 1) -> Purely | E6: 449 | F6: =Table1[[#This Row],[Unit Price ₹]]*(1-30%) -> 314.3
A7: WDKGFSC3 | B7: Purely Activated Charcoal Deep Cleanse Men’s Shampoo | C7: Personal Care (Shampoo & Soap) | D7: =LEFT(B7, FIND(" ", B7) - 1) -> Purely | E7: 349 | F7: =Table1[[#This Row],[Unit Price ₹]]*(1-30%) -> 244.3
A8: 60QV9086 | B8: Purely Fragrance-Free Ultra-Mild Sensitive Scalp Shampoo | C8: Personal Care (Shampoo & Soap) | D8: =LEFT(B8, FIND(" ", B8) - 1) -> Purely | E8: 375 | F8: =Table1[[#This Row],[Unit Price ₹]]*(1-30%) -> 262.5
A9: P4DFOT5Y | B9: Fresh Vitamin E & Aloe Vera Moisturizing Bar | C9: Personal Care (Shampoo & Soap) | D9: =LEFT(B9, FIND(" ", B9) - 1) -> Fresh | E9: 45 | F9: =Table1[[#This Row],[Unit Price ₹]]*(1-30%) -> 31.5
A10: FPBDJQCM | B10: Fresh Refreshing Lemon & Neem Germ Protection Soap | C10: Personal Care (Shampoo & Soap) | D10: =LEFT(B10, FIND(" ", B10) - 1) -> Fresh | E10: 40 | F10: =Table1[[#This Row],[Unit Price ₹]]*(1-30%) -> 28
A11: KD623HWM | B11: Fresh Rose Petal Cream Bathing Bar | C11: Personal Care (Shampoo & Soap) | D11: =LEFT(B11, FIND(" ", B11) - 1) -> Fresh | E11: 45 | F11: =Table1[[#This Row],[Unit Price ₹]]*(1-30%) -> 31.5
A12: 2MAW59E0 | B12: Purely Handcrafted Oatmeal & Honey Exfoliating Scrub Soap | C12: Personal Care (Shampoo & Soap) | D12: =LEFT(B12, FIND(" ", B12) - 1) -> Purely | E12: 125 | F12: =Table1[[#This Row],[Unit Price ₹]]*(1-30%) -> 87.5
A13: 7EQW23XA | B13: Purely Tea Tree & Salicylic Acid Acne-Control Bar | C13: Personal Care (Shampoo & Soap) | D13: =LEFT(B13, FIND(" ", B13) - 1) -> Purely | E13: 140 | F13: =Table1[[#This Row],[Unit Price ₹]]*(1-30%) -> 98
... A41: 1FVG7R94 | B41: Purely Detox Matcha Tea Powder | C41: Beverages (Juice & Tea) | D41: =LEFT(B41, FIND(" ", B41) - 1) -> Purely | E41: 599 | F41: =Table1[[#This Row],[Unit Price ₹]]*(1-30%) -> 419.3

Sheet Suppliers
A1: Supplier ID | B1: Supplier Name | C1: City | D1: Lead Time Days | E1: Rating | F1: Defect Rate
A2: O3AMMT2F | B2: Alpha Chemicals | C2: Mumbai | D2: 5 | E2: 4.5 | F2: 0.05
A3: TQB9XO97 | B3: Organic Farms Ltd | C3: Delhi | D3: 7 | E3: 4.2 | F3: 0.03
A4: CQ6GIM0Q | B4: Nature Foods Ltd | C4: Karnal | D4: 8 | E4: 4.8 | F4: 0.05
A5: RQ86YHH8 | B5: Green Agro Pvt Ltd | C5: Hisar | D5: 7 | E5: 4.2 | F5: 0.02
A6: B3P8KHJ2 | B6: Ram Foods Pvt Ltd | C6: Kolkata | D6: 4 | E6: 4 | F6: 0.03
A7: TQB9XO9 | B7: Herbal Tea Industries | C7: Assam | D7: 6 | E7: 4.5 | F7: 0.05
A8: TMX8P02 | B8: Suraj Mukhi Tea Pvt Ltd | C8: Siliguri | D8: 5 | E8: 4.2 | F8: 0.01

Sheet Warehouses
A1: Warehouse ID | B1: Warehouse Name | C1: City | D1: Capacity
A2: W101 | B2: North Hub | C2: Delhi | D2: 10000
A3: W102 | B3: East Hub | C3: Kolkata | D3: 8000
A4: W103 | B4: South Hub | C4: Bengaluru | D4: 12000
A5: W104 | B5: Bihar Hub | C5: Patna | D5: 7000

Sheet Orders
A1: Order ID | B1: Order Date | C1: Month | D1: Product ID | E1: Product Name | F1: Warehouse ID | G1: Quantity | H1: Unit Price | I1: Sales Amount | J1: DeliveryStatus
A2: =MID("0123456789ABCDEFGHIJKLMNOPQRSTUVWXYZ",RANDBETWEEN(1,36),1)&MID("0123456789ABCDEFGHIJKLMNOPQRSTUVWXYZ",RANDBETWEEN(1,36),1)&MID("0123456789ABCDEFGHIJKLMNOPQRSTUVWXYZ",RANDBETWEEN(1,36),1)&MID("0123456789ABCDEFGHIJKLMNOPQRSTUVWXYZ",RANDBETWEEN(1,36),1)&MID("0123456789ABCDEFGHIJKLMNOPQRSTUVWXYZ",RANDBETWEEN(1,36),1)&MID("0123456789ABCDEFGHIJKLMNOPQRSTUVWXYZ",RANDBETWEEN(1,36),1)&MID("0123456789ABCDEFGHIJKLMNOPQRSTUVWXYZ",RANDBETWEEN(1,36),1)&MID("0123456789ABCDEFGHIJKLMNOPQRSTUVWXYZ",RANDBETWEEN(1,36),1) -> GCFFNA5X | B2: 45677 | C2: =TEXT(B2,"mmm") -> Jan | D2: 5KCXE8ZI | E2: =VLOOKUP(D2,Products!$A:$B,2,FALSE) -> Fresh Anti-Dandruff Cool Mint Shampoo | F2: =INDEX({"W101","W102","W103","W104"},RANDBETWEEN(1,4)) -> W103 | G2: 65 | H2: =VLOOKUP(D2,Products!$A:$F,5,FALSE) -> 199 | I2: =H2*G2 -> 12935 | J2: =INDEX({"Delivered","Delayed"},RANDBETWEEN(1,2)) -> Delayed
A3: =MID("0123456789ABCDEFGHIJKLMNOPQRSTUVWXYZ",RANDBETWEEN(1,36),1)&MID("0123456789ABCDEFGHIJKLMNOPQRSTUVWXYZ",RANDBETWEEN(1,36),1)&MID("0123456789ABCDEFGHIJKLMNOPQRSTUVWXYZ",RANDBETWEEN(1,36),1)&MID("0123456789ABCDEFGHIJKLMNOPQRSTUVWXYZ",RANDBETWEEN(1,36),1)&MID("0123456789ABCDEFGHIJKLMNOPQRSTUVWXYZ",RANDBETWEEN(1,36),1)&MID("0123456789ABCDEFGHIJKLMNOPQRSTUVWXYZ",RANDBETWEEN(1,36),1)&MID("0123456789ABCDEFGHIJKLMNOPQRSTUVWXYZ",RANDBETWEEN(1,36),1)&MID("0123456789ABCDEFGHIJKLMNOPQRSTUVWXYZ",RANDBETWEEN(1,36),1) -> 5G3J100X | B3: 45678 | C3: =TEXT(B3,"mmm") -> Jan | D3: TOKW9ABP | E3: =VLOOKUP(D3,Products!$A:$B,2,FALSE) -> Fresh Smooth & Shiny Daily Silky Shampoo | F3: =INDEX({"W101","W102","W103","W104"},RANDBETWEEN(1,4)) -> W101 | G3: 87 | H3: =VLOOKUP(D3,Products!$A:$F,5,FALSE) -> 185 | I3: =H3*G3 -> 16095 | J3: =INDEX({"Delivered","Delayed"},RANDBETWEEN(1,2)) -> Delayed
A4: =MID("0123456789ABCDEFGHIJKLMNOPQRSTUVWXYZ",RANDBETWEEN(1,36),1)&MID("0123456789ABCDEFGHIJKLMNOPQRSTUVWXYZ",RANDBETWEEN(1,36),1)&MID("0123456789ABCDEFGHIJKLMNOPQRSTUVWXYZ",RANDBETWEEN(1,36),1)&MID("0123456789ABCDEFGHIJKLMNOPQRSTUVWXYZ",RANDBETWEEN(1,36),1)&MID("0123456789ABCDEFGHIJKLMNOPQRSTUVWXYZ",RANDBETWEEN(1,36),1)&MID("0123456789ABCDEFGHIJKLMNOPQRSTUVWXYZ",RANDBETWEEN(1,36),1)&MID("0123456789ABCDEFGHIJKLMNOPQRSTUVWXYZ",RANDBETWEEN(1,36),1)&MID("0123456789ABCDEFGHIJKLMNOPQRSTUVWXYZ",RANDBETWEEN(1,36),1) -> UDZZ8CYR | B4: 45679 | C4: =TEXT(B4,"mmm") -> Jan | D4: NEEPQGXJ | E4: =VLOOKUP(D4,Products!$A:$B,2,FALSE) -> Fresh Classic Salted Potato Chips (Party Pack) | F4: =INDEX({"W101","W102","W103","W104"},RANDBETWEEN(1,4)) -> W104 | G4: 184 | H4: =VLOOKUP(D4,Products!$A:$F,5,FALSE) -> 50 | I4: =H4*G4 -> 9200 | J4: =INDEX({"Delivered","Delayed"},RANDBETWEEN(1,2)) -> Delayed
A5: =MID("0123456789ABCDEFGHIJKLMNOPQRSTUVWXYZ",RANDBETWEEN(1,36),1)&MID("0123456789ABCDEFGHIJKLMNOPQRSTUVWXYZ",RANDBETWEEN(1,36),1)&MID("0123456789ABCDEFGHIJKLMNOPQRSTUVWXYZ",RANDBETWEEN(1,36),1)&MID("0123456789ABCDEFGHIJKLMNOPQRSTUVWXYZ",RANDBETWEEN(1,36),1)&MID("0123456789ABCDEFGHIJKLMNOPQRSTUVWXYZ",RANDBETWEEN(1,36),1)&MID("0123456789ABCDEFGHIJKLMNOPQRSTUVWXYZ",RANDBETWEEN(1,36),1)&MID("0123456789ABCDEFGHIJKLMNOPQRSTUVWXYZ",RANDBETWEEN(1,36),1)&MID("0123456789ABCDEFGHIJKLMNOPQRSTUVWXYZ",RANDBETWEEN(1,36),1) -> VV6DPO12 | B5: 45703 | C5: =TEXT(B5,"mmm") -> Feb | D5: B39QQXPS | E5: =VLOOKUP(D5,Products!$A:$B,2,FALSE) -> Purely Apple Cider Vinegar Hair Therapy Shampoo | F5: =INDEX({"W101","W102","W103","W104"},RANDBETWEEN(1,4)) -> W103 | G5: 144 | H5: =VLOOKUP(D5,Products!$A:$F,5,FALSE) -> 399 | I5: =H5*G5 -> 57456 | J5: =INDEX({"Delivered","Delayed"},RANDBETWEEN(1,2)) -> Delivered
A6: =MID("0123456789ABCDEFGHIJKLMNOPQRSTUVWXYZ",RANDBETWEEN(1,36),1)&MID("0123456789ABCDEFGHIJKLMNOPQRSTUVWXYZ",RANDBETWEEN(1,36),1)&MID("0123456789ABCDEFGHIJKLMNOPQRSTUVWXYZ",RANDBETWEEN(1,36),1)&MID("0123456789ABCDEFGHIJKLMNOPQRSTUVWXYZ",RANDBETWEEN(1,36),1)&MID("0123456789ABCDEFGHIJKLMNOPQRSTUVWXYZ",RANDBETWEEN(1,36),1)&MID("0123456789ABCDEFGHIJKLMNOPQRSTUVWXYZ",RANDBETWEEN(1,36),1)&MID("0123456789ABCDEFGHIJKLMNOPQRSTUVWXYZ",RANDBETWEEN(1,36),1)&MID("0123456789ABCDEFGHIJKLMNOPQRSTUVWXYZ",RANDBETWEEN(1,36),1) -> O7ZBX80D | B6: 45704 | C6: =TEXT(B6,"mmm") -> Feb | D6: L1RF73ZB | E6: =VLOOKUP(D6,Products!$A:$B,2,FALSE) -> Purely Argan Oil & Moroccan Clay Repair Shampoo | F6: =INDEX({"W101","W102","W103","W104"},RANDBETWEEN(1,4)) -> W101 | G6: 131 | H6: =VLOOKUP(D6,Products!$A:$F,5,FALSE) -> 449 | I6: =H6*G6 -> 58819 | J6: =INDEX({"Delivered","Delayed"},RANDBETWEEN(1,2)) -> Delayed
A7: =MID("0123456789ABCDEFGHIJKLMNOPQRSTUVWXYZ",RANDBETWEEN(1,36),1)&MID("0123456789ABCDEFGHIJKLMNOPQRSTUVWXYZ",RANDBETWEEN(1,36),1)&MID("0123456789ABCDEFGHIJKLMNOPQRSTUVWXYZ",RANDBETWEEN(1,36),1)&MID("0123456789ABCDEFGHIJKLMNOPQRSTUVWXYZ",RANDBETWEEN(1,36),1)&MID("0123456789ABCDEFGHIJKLMNOPQRSTUVWXYZ",RANDBETWEEN(1,36),1)&MID("0123456789ABCDEFGHIJKLMNOPQRSTUVWXYZ",RANDBETWEEN(1,36),1)&MID("0123456789ABCDEFGHIJKLMNOPQRSTUVWXYZ",RANDBETWEEN(1,36),1)&MID("0123456789ABCDEFGHIJKLMNOPQRSTUVWXYZ",RANDBETWEEN(1,36),1) -> I7DBPY4D | B7: 45705 | C7: =TEXT(B7,"mmm") -> Feb | D7: WDKGFSC3 | E7: =VLOOKUP(D7,Products!$A:$B,2,FALSE) -> Purely Activated Charcoal Deep Cleanse Men’s Shampoo | F7: =INDEX({"W101","W102","W103","W104"},RANDBETWEEN(1,4)) -> W103 | G7: 32 | H7: =VLOOKUP(D7,Products!$A:$F,5,FALSE) -> 349 | I7: =H7*G7 -> 11168 | J7: =INDEX({"Delivered","Delayed"},RANDBETWEEN(1,2)) -> Delivered
A8: =MID("0123456789ABCDEFGHIJKLMNOPQRSTUVWXYZ",RANDBETWEEN(1,36),1)&MID("0123456789ABCDEFGHIJKLMNOPQRSTUVWXYZ",RANDBETWEEN(1,36),1)&MID("0123456789ABCDEFGHIJKLMNOPQRSTUVWXYZ",RANDBETWEEN(1,36),1)&MID("0123456789ABCDEFGHIJKLMNOPQRSTUVWXYZ",RANDBETWEEN(1,36),1)&MID("0123456789ABCDEFGHIJKLMNOPQRSTUVWXYZ",RANDBETWEEN(1,36),1)&MID("0123456789ABCDEFGHIJKLMNOPQRSTUVWXYZ",RANDBETWEEN(1,36),1)&MID("0123456789ABCDEFGHIJKLMNOPQRSTUVWXYZ",RANDBETWEEN(1,36),1)&MID("0123456789ABCDEFGHIJKLMNOPQRSTUVWXYZ",RANDBETWEEN(1,36),1) -> 9FH7Y81I | B8: 45706 | C8: =TEXT(B8,"mmm") -> Feb | D8: 60QV9086 | E8: =VLOOKUP(D8,Products!$A:$B,2,FALSE) -> Purely Fragrance-Free Ultra-Mild Sensitive Scalp Shampoo | F8: =INDEX({"W101","W102","W103","W104"},RANDBETWEEN(1,4)) -> W103 | G8: 184 | H8: =VLOOKUP(D8,Products!$A:$F,5,FALSE) -> 375 | I8: =H8*G8 -> 69000 | J8: =INDEX({"Delivered","Delayed"},RANDBETWEEN(1,2)) -> Delivered
A9: =MID("0123456789ABCDEFGHIJKLMNOPQRSTUVWXYZ",RANDBETWEEN(1,36),1)&MID("0123456789ABCDEFGHIJKLMNOPQRSTUVWXYZ",RANDBETWEEN(1,36),1)&MID("0123456789ABCDEFGHIJKLMNOPQRSTUVWXYZ",RANDBETWEEN(1,36),1)&MID("0123456789ABCDEFGHIJKLMNOPQRSTUVWXYZ",RANDBETWEEN(1,36),1)&MID("0123456789ABCDEFGHIJKLMNOPQRSTUVWXYZ",RANDBETWEEN(1,36),1)&MID("0123456789ABCDEFGHIJKLMNOPQRSTUVWXYZ",RANDBETWEEN(1,36),1)&MID("0123456789ABCDEFGHIJKLMNOPQRSTUVWXYZ",RANDBETWEEN(1,36),1)&MID("0123456789ABCDEFGHIJKLMNOPQRSTUVWXYZ",RANDBETWEEN(1,36),1) -> UQ2ZHM3H | B9: 45707 | C9: =TEXT(B9,"mmm") -> Feb | D9: P4DFOT5Y | E9: =VLOOKUP(D9,Products!$A:$B,2,FALSE) -> Fresh Vitamin E & Aloe Vera Moisturizing Bar | F9: =INDEX({"W101","W102","W103","W104"},RANDBETWEEN(1,4)) -> W104 | G9: 175 | H9: =VLOOKUP(D9,Products!$A:$F,5,FALSE) -> 45 | I9: =H9*G9 -> 7875 | J9: =INDEX({"Delivered","Delayed"},RANDBETWEEN(1,2)) -> Delivered
A10: =MID("0123456789ABCDEFGHIJKLMNOPQRSTUVWXYZ",RANDBETWEEN(1,36),1)&MID("0123456789ABCDEFGHIJKLMNOPQRSTUVWXYZ",RANDBETWEEN(1,36),1)&MID("0123456789ABCDEFGHIJKLMNOPQRSTUVWXYZ",RANDBETWEEN(1,36),1)&MID("0123456789ABCDEFGHIJKLMNOPQRSTUVWXYZ",RANDBETWEEN(1,36),1)&MID("0123456789ABCDEFGHIJKLMNOPQRSTUVWXYZ",RANDBETWEEN(1,36),1)&MID("0123456789ABCDEFGHIJKLMNOPQRSTUVWXYZ",RANDBETWEEN(1,36),1)&MID("0123456789ABCDEFGHIJKLMNOPQRSTUVWXYZ",RANDBETWEEN(1,36),1)&MID("0123456789ABCDEFGHIJKLMNOPQRSTUVWXYZ",RANDBETWEEN(1,36),1) -> N0K6HCA8 | B10: 45708 | C10: =TEXT(B10,"mmm") -> Feb | D10: FPBDJQCM | E10: =VLOOKUP(D10,Products!$A:$B,2,FALSE) -> Fresh Refreshing Lemon & Neem Germ Protection Soap | F10: =INDEX({"W101","W102","W103","W104"},RANDBETWEEN(1,4)) -> W103 | G10: 125 | H10: =VLOOKUP(D10,Products!$A:$F,5,FALSE) -> 40 | I10: =H10*G10 -> 5000 | J10: =INDEX({"Delivered","Delayed"},RANDBETWEEN(1,2)) -> Delivered
A11: =MID("0123456789ABCDEFGHIJKLMNOPQRSTUVWXYZ",RANDBETWEEN(1,36),1)&MID("0123456789ABCDEFGHIJKLMNOPQRSTUVWXYZ",RANDBETWEEN(1,36),1)&MID("0123456789ABCDEFGHIJKLMNOPQRSTUVWXYZ",RANDBETWEEN(1,36),1)&MID("0123456789ABCDEFGHIJKLMNOPQRSTUVWXYZ",RANDBETWEEN(1,36),1)&MID("0123456789ABCDEFGHIJKLMNOPQRSTUVWXYZ",RANDBETWEEN(1,36),1)&MID("0123456789ABCDEFGHIJKLMNOPQRSTUVWXYZ",RANDBETWEEN(1,36),1)&MID("0123456789ABCDEFGHIJKLMNOPQRSTUVWXYZ",RANDBETWEEN(1,36),1)&MID("0123456789ABCDEFGHIJKLMNOPQRSTUVWXYZ",RANDBETWEEN(1,36),1) -> M8IRE9F6 | B11: 45709 | C11: =TEXT(B11,"mmm") -> Feb | D11: KD623HWM | E11: =VLOOKUP(D11,Products!$A:$B,2,FALSE) -> Fresh Rose Petal Cream Bathing Bar | F11: =INDEX({"W101","W102","W103","W104"},RANDBETWEEN(1,4)) -> W101 | G11: 187 | H11: =VLOOKUP(D11,Products!$A:$F,5,FALSE) -> 45 | I11: =H11*G11 -> 8415 | J11: =INDEX({"Delivered","Delayed"},RANDBETWEEN(1,2)) -> Delivered
A12: =MID("0123456789ABCDEFGHIJKLMNOPQRSTUVWXYZ",RANDBETWEEN(1,36),1)&MID("0123456789ABCDEFGHIJKLMNOPQRSTUVWXYZ",RANDBETWEEN(1,36),1)&MID("0123456789ABCDEFGHIJKLMNOPQRSTUVWXYZ",RANDBETWEEN(1,36),1)&MID("0123456789ABCDEFGHIJKLMNOPQRSTUVWXYZ",RANDBETWEEN(1,36),1)&MID("0123456789ABCDEFGHIJKLMNOPQRSTUVWXYZ",RANDBETWEEN(1,36),1)&MID("0123456789ABCDEFGHIJKLMNOPQRSTUVWXYZ",RANDBETWEEN(1,36),1)&MID("0123456789ABCDEFGHIJKLMNOPQRSTUVWXYZ",RANDBETWEEN(1,36),1)&MID("0123456789ABCDEFGHIJKLMNOPQRSTUVWXYZ",RANDBETWEEN(1,36),1) -> GGUOMOVF | B12: 45710 | C12: =TEXT(B12,"mmm") -> Feb | D12: 2MAW59E0 | E12: =VLOOKUP(D12,Products!$A:$B,2,FALSE) -> Purely Handcrafted Oatmeal & Honey Exfoliating Scrub Soap | F12: =INDEX({"W101","W102","W103","W104"},RANDBETWEEN(1,4)) -> W104 | G12: 176 | H12: =VLOOKUP(D12,Products!$A:$F,5,FALSE) -> 125 | I12: =H12*G12 -> 22000 | J12: =INDEX({"Delivered","Delayed"},RANDBETWEEN(1,2)) -> Delayed
A13: =MID("0123456789ABCDEFGHIJKLMNOPQRSTUVWXYZ",RANDBETWEEN(1,36),1)&MID("0123456789ABCDEFGHIJKLMNOPQRSTUVWXYZ",RANDBETWEEN(1,36),1)&MID("0123456789ABCDEFGHIJKLMNOPQRSTUVWXYZ",RANDBETWEEN(1,36),1)&MID("0123456789ABCDEFGHIJKLMNOPQRSTUVWXYZ",RANDBETWEEN(1,36),1)&MID("0123456789ABCDEFGHIJKLMNOPQRSTUVWXYZ",RANDBETWEEN(1,36),1)&MID("0123456789ABCDEFGHIJKLMNOPQRSTUVWXYZ",RANDBETWEEN(1,36),1)&MID("0123456789ABCDEFGHIJKLMNOPQRSTUVWXYZ",RANDBETWEEN(1,36),1)&MID("0123456789ABCDEFGHIJKLMNOPQRSTUVWXYZ",RANDBETWEEN(1,36),1) -> 1ONZLK1R | B13: 45711 | C13: =TEXT(B13,"mmm") -> Feb | D13: 7EQW23XA | E13: =VLOOKUP(D13,Products!$A:$B,2,FALSE) -> Purely Tea Tree & Salicylic Acid Acne-Control Bar | F13: =INDEX({"W101","W102","W103","W104"},RANDBETWEEN(1,4)) -> W101 | G13: 148 | H13: =VLOOKUP(D13,Products!$A:$F,5,FALSE) -> 140 | I13: =H13*G13 -> 20720 | J13: =INDEX({"Delivered","Delayed"},RANDBETWEEN(1,2)) -> Delivered
... A205: =MID("0123456789ABCDEFGHIJKLMNOPQRSTUVWXYZ",RANDBETWEEN(1,36),1)&MID("0123456789ABCDEFGHIJKLMNOPQRSTUVWXYZ",RANDBETWEEN(1,36),1)&MID("0123456789ABCDEFGHIJKLMNOPQRSTUVWXYZ",RANDBETWEEN(1,36),1)&MID("0123456789ABCDEFGHIJKLMNOPQRSTUVWXYZ",RANDBETWEEN(1,36),1)&MID("0123456789ABCDEFGHIJKLMNOPQRSTUVWXYZ",RANDBETWEEN(1,36),1)&MID("0123456789ABCDEFGHIJKLMNOPQRSTUVWXYZ",RANDBETWEEN(1,36),1)&MID("0123456789ABCDEFGHIJKLMNOPQRSTUVWXYZ",RANDBETWEEN(1,36),1)&MID("0123456789ABCDEFGHIJKLMNOPQRSTUVWXYZ",RANDBETWEEN(1,36),1) -> ZR2QFRHQ | B205: 45838 | C205: =TEXT(B205,"mmm") -> Jun | D205: OK1CMHD6 | E205: =VLOOKUP(D205,Products!$A:$B,2,FALSE) -> Fresh Refreshing Alphonso Mango Drink | F205: =INDEX({"W101","W102","W103","W104"},RANDBETWEEN(1,4)) -> W102 | G205: 140 | H205: =VLOOKUP(D205,Products!$A:$F,5,FALSE) -> 99 | I205: =H205*G205 -> 13860 | J205: =INDEX({"Delivered","Delayed"},RANDBETWEEN(1,2)) -> Delivered

Sheet Inventory
A1: SKU | B1: WarehouseID | C1: CurrentStock | D1: SafetyStock | E1: ReorderPoint | F1: Unit Cost ₹ | G1: Product Value ₹ | H1: Inventory Status
A2: 7GPA08FD | B2: W103 | C2: 150 | D2: 270 | E2: 212 | F2: =VLOOKUP(A:A,Products!A:F,6,FALSE) -> 28 | G2: =C2*F2 -> 4200 | H2: =IF(C2<D2,"High Risk","Safe") -> High Risk
A3: 1FVG7R94 | B3: W103 | C3: 150 | D3: 348 | E3: 314 | F3: =VLOOKUP(A:A,Products!A:F,6,FALSE) -> 419.3 | G3: =C3*F3 -> 62895 | H3: =IF(C3<D3,"High Risk","Safe") -> High Risk
A4: IS258KLL | B4: W102 | C4: 158 | D4: 333 | E4: 298 | F4: =VLOOKUP(A:A,Products!A:F,6,FALSE) -> 42 | G4: =C4*F4 -> 6636 | H4: =IF(C4<D4,"High Risk","Safe") -> High Risk
A5: X5UTVQQ9 | B5: W101 | C5: 160 | D5: 265 | E5: 486 | F5: =VLOOKUP(A:A,Products!A:F,6,FALSE) -> 87.5 | G5: =C5*F5 -> 14000 | H5: =IF(C5<D5,"High Risk","Safe") -> High Risk
A6: 1FVG7R94 | B6: W102 | C6: 160 | D6: 281 | E6: 424 | F6: =VLOOKUP(A:A,Products!A:F,6,FALSE) -> 419.3 | G6: =C6*F6 -> 67088 | H6: =IF(C6<D6,"High Risk","Safe") -> High Risk
A7: 7TOPPUAS | B7: W104 | C7: 163 | D7: 303 | E7: 280 | F7: =VLOOKUP(A:A,Products!A:F,6,FALSE) -> 104.3 | G7: =C7*F7 -> 17000.9 | H7: =IF(C7<D7,"High Risk","Safe") -> High Risk
A8: WDKGFSC3 | B8: W103 | C8: 167 | D8: 251 | E8: 308 | F8: =VLOOKUP(A:A,Products!A:F,6,FALSE) -> 244.3 | G8: =C8*F8 -> 40798.1 | H8: =IF(C8<D8,"High Risk","Safe") -> High Risk
A9: B39QQXPS | B9: W101 | C9: 169 | D9: 312 | E9: 423 | F9: =VLOOKUP(A:A,Products!A:F,6,FALSE) -> 279.3 | G9: =C9*F9 -> 47201.7 | H9: =IF(C9<D9,"High Risk","Safe") -> High Risk
A10: 440D5XFY | B10: W102 | C10: 170 | D10: 272 | E10: 339 | F10: =VLOOKUP(A:A,Products!A:F,6,FALSE) -> 104.3 | G10: =C10*F10 -> 17731 | H10: =IF(C10<D10,"High Risk","Safe") -> High Risk
A11: L1RF73ZB | B11: W103 | C11: 171 | D11: 323 | E11: 470 | F11: =VLOOKUP(A:A,Products!A:F,6,FALSE) -> 314.3 | G11: =C11*F11 -> 53745.3 | H11: =IF(C11<D11,"High Risk","Safe") -> High Risk
A12: LIDWWTRO | B12: W101 | C12: 171 | D12: 306 | E12: 421 | F12: =VLOOKUP(A:A,Products!A:F,6,FALSE) -> 297.5 | G12: =C12*F12 -> 50872.5 | H12: =IF(C12<D12,"High Risk","Safe") -> High Risk
A13: Q92TVB4C | B13: W102 | C13: 172 | D13: 312 | E13: 435 | F13: =VLOOKUP(A:A,Products!A:F,6,FALSE) -> 157.5 | G13: =C13*F13 -> 27090 | H13: =IF(C13<D13,"High Risk","Safe") -> High Risk
... A150: 7GPA08FD | B150: W101 | C150: 497 | D150: 262 | E150: 253 | F150: =VLOOKUP(A:A,Products!A:F,6,FALSE) -> 28 | G150: =C150*F150 -> 13916 | H150: =IF(C150<D150,"High Risk","Safe") -> Safe
G1048576: =SUM(G1:G1048575) -> 6888673.4

Sheet Shipments
A1: ShipmentID | B1: SupplierID | C1: ProductID | D1: Product Name | E1: WarehouseID | F1: ShipmentDate | G1: ExpectedDelivery | H1: ActualDelivery | I1: QuantityShipped | J1: TransportCost | K1: DelayDays | L1: ShipmentStatus
A2: AMDM5TTC | B2: TQB9XO97 | C2: 7GPA08FD | D2: =VLOOKUP(C2,Products!$A:$B,2,FALSE) -> Fresh Glucose Power Biscuits (Value Pack) | E2: W103 | F2: 45818 | G2: 45825 | H2: 45826 | I2: 695 | J2: 6182 | K2: =H2-G2 -> 1 | L2: =IF(K2=0,"On Time",IF(K2<=5,"Minor Delay",IF(K2<=10,"Major Delay","Critical Delay"))) -> Minor Delay
A3: OBQADTD6 | B3: TQB9XO9 | C3: 1FVG7R94 | D3: =VLOOKUP(C3,Products!$A:$B,2,FALSE) -> Purely Detox Matcha Tea Powder | E3: W103 | F3: 45906 | G3: 45910 | H3: 45923 | I3: 514 | J3: 12639 | K3: =H3-G3 -> 13 | L3: =IF(K3=0,"On Time",IF(K3<=5,"Minor Delay",IF(K3<=10,"Major Delay","Critical Delay"))) -> Critical Delay
A4: C430CG2U | B4: TQB9XO97 | C4: IS258KLL | D4: =VLOOKUP(C4,Products!$A:$B,2,FALSE) -> Fresh Crunchy Choco-Chip Cookies | E4: W102 | F4: 45772 | G4: 45775 | H4: 45775 | I4: 530 | J4: 12755 | K4: =H4-G4 -> 0 | L4: =IF(K4=0,"On Time",IF(K4<=5,"Minor Delay",IF(K4<=10,"Major Delay","Critical Delay"))) -> On Time
A5: R2ZOPDJQ | B5: TQB9XO97 | C5: X5UTVQQ9 | D5: =VLOOKUP(C5,Products!$A:$B,2,FALSE) -> Fresh 100% Pure Mixed Fruit Juice | E5: W101 | F5: 45715 | G5: 45721 | H5: 45721 | I5: 593 | J5: 13536 | K5: =H5-G5 -> 0 | L5: =IF(K5=0,"On Time",IF(K5<=5,"Minor Delay",IF(K5<=10,"Major Delay","Critical Delay"))) -> On Time
A6: FJNEBK3Z | B6: TQB9XO9 | C6: 1FVG7R94 | D6: =VLOOKUP(C6,Products!$A:$B,2,FALSE) -> Purely Detox Matcha Tea Powder | E6: W102 | F6: 45799 | G6: 45803 | H6: 45812 | I6: 590 | J6: 9361 | K6: =H6-G6 -> 9 | L6: =IF(K6=0,"On Time",IF(K6<=5,"Minor Delay",IF(K6<=10,"Major Delay","Critical Delay"))) -> Major Delay
A7: UEYAO3MW | B7: O3AMMT2F | C7: 7TOPPUAS | D7: =VLOOKUP(C7,Products!$A:$B,2,FALSE) -> Fresh Lemon Power Detergent Powder (Tough Stain Remover) | E7: W104 | F7: 45978 | G7: 45983 | H7: 45983 | I7: 696 | J7: 13772 | K7: =H7-G7 -> 0 | L7: =IF(K7=0,"On Time",IF(K7<=5,"Minor Delay",IF(K7<=10,"Major Delay","Critical Delay"))) -> On Time
A8: Y27685VU | B8: TQB9XO97 | C8: WDKGFSC3 | D8: =VLOOKUP(C8,Products!$A:$B,2,FALSE) -> Purely Activated Charcoal Deep Cleanse Men’s Shampoo | E8: W103 | F8: 45787 | G8: 45790 | H8: 45799 | I8: 670 | J8: 14015 | K8: =H8-G8 -> 9 | L8: =IF(K8=0,"On Time",IF(K8<=5,"Minor Delay",IF(K8<=10,"Major Delay","Critical Delay"))) -> Major Delay
A9: XGRZRVEZ | B9: CQ6GIM0Q | C9: B39QQXPS | D9: =VLOOKUP(C9,Products!$A:$B,2,FALSE) -> Purely Apple Cider Vinegar Hair Therapy Shampoo | E9: W101 | F9: 45773 | G9: 45779 | H9: 45793 | I9: 508 | J9: 12013 | K9: =H9-G9 -> 14 | L9: =IF(K9=0,"On Time",IF(K9<=5,"Minor Delay",IF(K9<=10,"Major Delay","Critical Delay"))) -> Critical Delay
A10: MU8XNSZ0 | B10: RQ86YHH8 | C10: 440D5XFY | D10: =VLOOKUP(C10,Products!$A:$B,2,FALSE) -> Purely Almond & Chia Seed Millet Oats Biscuits | E10: W102 | F10: 45731 | G10: 45737 | H10: 45747 | I10: 618 | J10: 13717 | K10: =H10-G10 -> 10 | L10: =IF(K10=0,"On Time",IF(K10<=5,"Minor Delay",IF(K10<=10,"Major Delay","Critical Delay"))) -> Major Delay
A11: 91Z9E2GQ | B11: B3P8KHJ2 | C11: L1RF73ZB | D11: =VLOOKUP(C11,Products!$A:$B,2,FALSE) -> Purely Argan Oil & Moroccan Clay Repair Shampoo | E11: W103 | F11: 45983 | G11: 45989 | H11: 45989 | I11: 689 | J11: 14453 | K11: =H11-G11 -> 0 | L11: =IF(K11=0,"On Time",IF(K11<=5,"Minor Delay",IF(K11<=10,"Major Delay","Critical Delay"))) -> On Time
A12: 6NEGUM94 | B12: TQB9XO97 | C12: LIDWWTRO | D12: =VLOOKUP(C12,Products!$A:$B,2,FALSE) -> Purely Plant-Based Baby Laundry Detergent (Hypoallergenic) | E12: W101 | F12: 45866 | G12: 45872 | H12: 45884 | I12: 652 | J12: 14819 | K12: =H12-G12 -> 12 | L12: =IF(K12=0,"On Time",IF(K12<=5,"Minor Delay",IF(K12<=10,"Major Delay","Critical Delay"))) -> Critical Delay
A13: HFTKC58X | B13: B3P8KHJ2 | C13: Q92TVB4C | D13: =VLOOKUP(C13,Products!$A:$B,2,FALSE) -> Fresh 2-in-1 Shampoo + Conditioner for Kids (Mango Flavor) | E13: W102 | F13: 45955 | G13: 45959 | H13: 45959 | I13: 570 | J13: 9429 | K13: =H13-G13 -> 0 | L13: =IF(K13=0,"On Time",IF(K13<=5,"Minor Delay",IF(K13<=10,"Major Delay","Critical Delay"))) -> On Time
... A87: OZTICAYY | B87: B3P8KHJ2 | C87: 5K3AAX91 | D87: =VLOOKUP(C87,Products!$A:$B,2,FALSE) -> Purely Eucalyptus Eco-Friendly Detergent Sheets | E87: W101 | F87: 45811 | G87: 45817 | H87: 45828 | I87: 584 | J87: 14201 | K87: =H87-G87 -> 11 | L87: =IF(K87=0,"On Time",IF(K87<=5,"Minor Delay",IF(K87<=10,"Major Delay","Critical Delay"))) -> Critical Delay

Sheet Forecast
A1: ForecastMonth | B1: Product ID | C1: ActualDemand | D1: ForecastDemand | E1: ForecastAccuracy | F1: DemandVariance
A2: 2025-01 | B2: 5KCXE8ZI | C2: 65 | D2: 69 | E2: 93.85 | F2: -4
A3: 2025-01 | B3: 7GPA08FD | C3: 81 | D3: 78 | E3: 96.3 | F3: 3
A4: 2025-01 | B4: B39QQXPS | C4: 121 | D4: 114 | E4: 94.21 | F4: 7
A5: 2025-01 | B5: HT7CSM4D | C5: 156 | D5: 166 | E5: 93.59 | F5: -10
A6: 2025-01 | B6: I24Q3YSV | C6: 60 | D6: 61 | E6: 98.33 | F6: -1
A7: 2025-01 | B7: IS258KLL | C7: 45 | D7: 43 | E7: 95.56 | F7: 2
A8: 2025-01 | B8: K5JEEZ29 | C8: 137 | D8: 140 | E8: 97.81 | F8: -3
A9: 2025-01 | B9: NEEPQGXJ | C9: 397 | D9: 370 | E9: 93.2 | F9: 27
A10: 2025-01 | B10: OGNIEK8R | C10: 95 | D10: 100 | E10: 94.74 | F10: -5
A11: 2025-01 | B11: P4DFOT5Y | C11: 126 | D11: 123 | E11: 97.62 | F11: 3
A12: 2025-01 | B12: SGIS5I27 | C12: 193 | D12: 182 | E12: 94.3 | F12: 11
A13: 2025-01 | B13: TOKW9ABP | C13: 301 | D13: 297 | E13: 98.67 | F13: 4
... A164: 2025-12 | B164: WDKGFSC3 | C164: 253 | D164: 250 | E164: 98.81 | F164: 3

Sheet KPI Calculations
A1: KPI Name | B1: Value | C1: Status
A2: Total Revenue | B2: =SUM(Orders!I:I) -> 4637350 | C2: Good
A3: Total Orders | B3: =COUNTA(Orders!A2:A205) -> 204 | C3: Good
A4: Average Order Value | B4: =B2/B3 -> 22732.108 | C4: Good
A5: OTIF% | B5: =COUNTIF(Orders!J:J,"Delivered")/(COUNTA(Orders!A:A)-1) -> 0.49019608 | C5: =IF(B5>=95%,"Good",IF(B5>=85%,"Warning","Critical")) -> Critical
A6: Delayed Orders% | B6: =COUNTIF(Orders!J:J,"Delayed")/(COUNTA(Orders!A:A)-1) -> 0.50980392 | C6: =IF(B6<=5%,"Good",IF(B6<=15%,"Warning","Critical")) -> Critical
A7: Total Shipments | B7: =COUNTA(Shipments!A:A)-1 -> 86 | C7: Good
A8: Shipment On Time% | B8: =COUNTIF(Shipments!L:L,"On Time")/$B$7 -> 0.36046512 | C8: =IF(B8>=90%,"Good",IF(B8>=75%,"Warning","Critical")) -> Critical
A9: Shipment Minor Delay% | B9: =COUNTIF(Shipments!L:L,"Minor Delay")/$B$7 -> 0.30232558 | C9: =IF(B9<=10%,"Good",IF(B9<=25%,"Warning","Critical")) -> Critical
A10: Shipment Major Delay% | B10: =COUNTIF(Shipments!L:L,"Major Delay")/$B$7 -> 0.1627907 | C10: =IF(B10<=5%,"Good",IF(B10<=10%,"Warning","Critical")) -> Critical
A11: Shipment Critical Delay % | B11: =COUNTIF(Shipments!L:L,"Critical Delay")/$B$7 -> 0.1744186 | C11: =IF(B11<=2%,"Good",IF(B11<=5%,"Warning","Critical")) -> Critical
A12: Forecast Accuracy% | B12: =AVERAGE(Forecast!E:E) -> 95.070736 | C12: =IF(B12>=90,"Good",IF(B12>=80,"Warning","Critical")) -> Good
A13: Inventory Value | B13: =SUM(Inventory!G:G) -> 13777347 | C13: Monitor
A14: High Risk SKUs | B14: =COUNTIF(Inventory!H:H,"High Risk") -> 58 | C14: =IF(B14<=5,"Good",IF(B14<=15,"Warning","Critical")) -> Critical
A15: Stock Out Risk % | B15: =COUNTIF(Inventory!H:H,"High Risk")/(COUNTA(Inventory!A:A)-1) -> 0.38926174 | C15: =IF(B15<=5%,"Good",IF(B15<=10%,"Warning","Critical")) -> Critical
